cryocanvas/__init__.py
cryocanvas/_widget.py
cryocanvas/app.py
cryocanvas/napari.yaml
cryocanvas/_tests/__init__.py
cryocanvas/_tests/test_widget.py
cryocanvas-0.0.1.dist-info/LICENSE
cryocanvas-0.0.1.dist-info/METADATA
cryocanvas-0.0.1.dist-info/WHEEL
cryocanvas-0.0.1.dist-info/entry_points.txt
cryocanvas-0.0.1.dist-info/top_level.txt
cryocanvas-0.0.1.dist-info/RECORD
